README.rst
setup.py
django_winds/__init__.py
django_winds/api.py
django_winds/models.py
django_winds/tests.py
django_winds/urls.py
django_winds.egg-info/PKG-INFO
django_winds.egg-info/SOURCES.txt
django_winds.egg-info/dependency_links.txt
django_winds.egg-info/requires.txt
django_winds.egg-info/top_level.txt
django_winds/backends/__init__.py
django_winds/backends/base.py
django_winds/backends/tests.py
django_winds/backends/ucar.py