Metadata-Version: 1.1
Name: django-winds
Version: 0.1
Summary: A tool to collect and serve wind prediction data.
Home-page: https://bitbucket.org/bilgecode/django-winds
Author: Benjamin Stookey
Author-email: ben@bilgecode.org
License: LICENSE
Platform: UNKNOWN
Classifier: Development Status :: 4 - Beta
Classifier: Environment :: Web Environment
Classifier: Framework :: Django
Classifier: Intended Audience :: Developers
Classifier: License :: OSI Approved :: BSD License
Classifier: Operating System :: OS Independent
Classifier: Programming Language :: Python
Classifier: Topic :: Utilities
